.gitignore
CHANGES.txt
MANIFEST.in
README.md
README.txt
setup.cfg
setup.py
pcommerce/__init__.py
pcommerce.shipment.digital.egg-info/PKG-INFO
pcommerce.shipment.digital.egg-info/SOURCES.txt
pcommerce.shipment.digital.egg-info/dependency_links.txt
pcommerce.shipment.digital.egg-info/entry_points.txt
pcommerce.shipment.digital.egg-info/namespace_packages.txt
pcommerce.shipment.digital.egg-info/not-zip-safe
pcommerce.shipment.digital.egg-info/requires.txt
pcommerce.shipment.digital.egg-info/top_level.txt
pcommerce/shipment/__init__.py
pcommerce/shipment/digital/__init__.py
pcommerce/shipment/digital/configure.zcml
pcommerce/shipment/digital/data.py
pcommerce/shipment/digital/interfaces.py
pcommerce/shipment/digital/plugin.py
pcommerce/shipment/digital/browser/__init__.py
pcommerce/shipment/digital/browser/base.py
pcommerce/shipment/digital/browser/configure.zcml
pcommerce/shipment/digital/browser/confirmation.pt
pcommerce/shipment/digital/browser/confirmation.py
pcommerce/shipment/digital/browser/icon.gif
pcommerce/shipment/digital/browser/logo.png
pcommerce/shipment/digital/browser/overview.pt
pcommerce/shipment/digital/browser/overview.py
pcommerce/shipment/digital/browser/shipment.py
pcommerce/shipment/digital/i18n/pcommerce.pot
pcommerce/shipment/digital/profiles/default/metadata.xml
pcommerce/shipment/digital/profiles/default/propertiestool.xml