Metadata-Version: 1.1
Name: pcommerce.shipment.digital
Version: 0.2
Summary: Provides a pick up shipment plugin for PCommerce
Home-page: https://svn.plone.org/svn/collective/pcommerce.shipment.digital
Author: Steffen Lindner
Author-email: gomez@flexiabel.de
License: GPL
Platform: UNKNOWN
Classifier: Programming Language :: Python
Classifier: Topic :: Software Development :: Libraries :: Python Modules
